marchingsquares-0.1.1.dist-info/METADATA
marchingsquares-0.1.1.dist-info/WHEEL
marchingsquares-0.1.1.dist-info/licenses/LICENSE
marchingsquares.libs/libgcc_s-b5472b99.so.1
marchingsquares/__init__.py
marchingsquares/_marchingsquares.cpython-310-i386-linux-gnu.so
marchingsquares/_marchingsquares.pyi
marchingsquares/py.typed
marchingsquares-0.1.1.dist-info/RECORD
